google_docs_mcp/__init__.py
google_docs_mcp/cli.py
google_docs_mcp/clients/__init__.py
google_docs_mcp/clients/docs_client.py
google_docs_mcp/clients/drive_client.py
google_docs_mcp/clients/google_auth.py
google_docs_mcp/config.py
google_docs_mcp/links.py
google_docs_mcp/models.py
google_docs_mcp/server.py
google_docs_mcp/storage.py
google_docs_mcp/tools/__init__.py
google_docs_mcp/tools/docs_tools.py
google_docs_mcp/tools/drive_tools.py
google_docs_mcp-0.1.0.dist-info/WHEEL
google_docs_mcp-0.1.0.dist-info/entry_points.txt
google_docs_mcp-0.1.0.dist-info/METADATA
google_docs_mcp-0.1.0.dist-info/RECORD
