Metadata-Version: 2.3
Name: google-docs-mcp
Version: 0.1.0
Summary: MCP server for Google Docs
Author: Jag_k
Author-email: Jag_k <30597878+jag-k@users.noreply.github.com>
Requires-Dist: pydantic-settings>=2.10.1
Requires-Dist: pydantic>=2.11.7
Requires-Dist: google-auth>=2.40.3
Requires-Dist: google-auth-oauthlib>=1.2.2
Requires-Dist: google-api-python-client>=2.179.0
Requires-Dist: tenacity>=9.1.2
Requires-Dist: markdownify>=1.2.0
Requires-Dist: mcp>=1.13.1
Requires-Dist: platformdirs>=4.4.0
Requires-Dist: fastmcp>=2.11.3
Requires-Dist: xdg-base-dirs>=6.0.2
Requires-Python: >=3.13
